TASK/2/task2/GHDL_MHL2 2/Morse_ywz.vhd
library ieee; use ieee.std_logic_1164.all; use ieee.numeric_std.all;
entity MorseYWZ is
port ( X : in unsigned(5 downto 0):=(others=> '0'); -- I/O initializations are only relevant for simulations.
Y, STOP : out std_logic:='0' );
end entity;
architecture behavioral of MorseYWZ is
signal a, b, c, d, e, f : std_logic:='0';
signal Y00, Y01, Y10, Y11 : std_logic:='0';
begin
-- renaming of signals
a<= X(5); b<= X(4); c<= X(3); d<= X(2); e<= X(1); f<= X(0);
Y00 <= (c and not e) or (f and not c) or (f and not d) or (e and not c and not d);
Y01 <= (d and e ) or (d and f) or (e and f) or (f and not c);
Y10 <= (d and f) or (e and f) or (c and d and e) or (d and not c and not e);
Y11 <= (e and not c and not d) or (f and not c and not d);
-- Multiplexer -----------------------------
with X(5 downto 4) select
Y <= Y00 when "00", Y01 when "01", Y10 when "10",
Y11 when others; -- 2 std_logic bits can have 9*9 values!!!
STOP<= a and b and f; -- 2**5 + 2**4 + 1 = 49
end architecture;

TASK/2/task2/GHDL_MHL2 2/testbench_YWZ.vhd
library ieee; use ieee.std_logic_1164.all; use ieee.numeric_std.all;
library work;
entity testbench_YWZ is end entity;

architecture rtl of testbench_YWZ is
signal x:unsigned(5 downto 0):=(others=>'0');
signal y, stop : std_logic:='0';

begin -- architecture, we implement all only by Concurrent Statements
   iywz : entity work.MorseYWZ port map (x,y,stop);
   x<= x+1 after 10 ns;	
end architecture;

TASK/2/task2/GHDL_MHL2 2/simulation/MySim.vcd
$date
  Wed Nov 05 00:01:07 2025
$end
$version
  GHDL v0
$end
$timescale
  1 fs
$end
$scope module standard $end
$upscope $end
$scope module textio $end
$upscope $end
$scope module std_logic_1164 $end
$upscope $end
$scope module numeric_std $end
$upscope $end
$scope module testbench_ywz $end
$var reg 6 ! x[5:0] $end
$var reg 1 " y $end
$var reg 1 # stop $end
$scope module iywz $end
$var reg 6 $ x[5:0] $end
$var reg 1 % y $end
$var reg 1 & stop $end
$var reg 1 ' a $end
$var reg 1 ( b $end
$var reg 1 ) c $end
$var reg 1 * d $end
$var reg 1 + e $end
$var reg 1 , f $end
$var reg 1 - y00 $end
$var reg 1 . y01 $end
$var reg 1 / y10 $end
$var reg 1 0 y11 $end
$upscope $end
$upscope $end
$enddefinitions $end
#0
b000000 !
0"
0#
b000000 $
0%
0&
0'
0(
0)
0*
0+
0,
0-
0.
0/
00
#10000000
b000001 !
1"
b000001 $
1%
1,
1-
1.
10
#20000000
b000010 !
b000010 $
1+
0,
0.
#30000000
b000011 !
b000011 $
1,
1.
1/
#40000000
b000100 !
0"
b000100 $
0%
1*
0+
0,
0-
0.
00
#50000000
b000101 !
1"
b000101 $
1%
1,
1-
1.
#60000000
b000110 !
0"
b000110 $
0%
1+
0,
0-
0/
#70000000
b000111 !
1"
b000111 $
1%
1,
1-
1/
#80000000
b001000 !
b001000 $
1)
0*
0+
0,
0.
0/
#90000000
b001001 !
b001001 $
1,
#100000000
b001010 !
0"
b001010 $
0%
1+
0,
0-
#110000000
b001011 !
1"
b001011 $
1%
1,
1-
1.
1/
#120000000
b001100 !
b001100 $
1*
0+
0,
0.
0/
#130000000
b001101 !
b001101 $
1,
1.
1/
#140000000
b001110 !
0"
b001110 $
0%
1+
0,
0-
#150000000
b001111 !
b001111 $
1,
#160000000
b010000 !
0"
b010000 $
0%
1(
0)
0*
0+
0,
0.
0/
#170000000
b010001 !
1"
b010001 $
1%
1,
1-
1.
10
#180000000
b010010 !
0"
b010010 $
0%
1+
0,
0.
#190000000
b010011 !
1"
b010011 $
1%
1,
1.
1/
#200000000
b010100 !
0"
b010100 $
0%
1*
0+
0,
0-
0.
00
#210000000
b010101 !
1"
b010101 $
1%
1,
1-
1.
#220000000
b010110 !
b010110 $
1+
0,
0-
0/
#230000000
b010111 !
b010111 $
1,
1-
1/
#240000000
b011000 !
0"
b011000 $
0%
1)
0*
0+
0,
0.
0/
#250000000
b011001 !
b011001 $
1,
#260000000
b011010 !
b011010 $
1+
0,
0-
#270000000
b011011 !
1"
b011011 $
1%
1,
1-
1.
1/
#280000000
b011100 !
0"
b011100 $
0%
1*
0+
0,
0.
0/
#290000000
b011101 !
1"
b011101 $
1%
1,
1.
1/
#300000000
b011110 !
b011110 $
1+
0,
0-
#310000000
b011111 !
b011111 $
1,
#320000000
b100000 !
0"
b100000 $
0%
1'
0(
0)
0*
0+
0,
0.
0/
#330000000
b100001 !
b100001 $
1,
1-
1.
10
#340000000
b100010 !
b100010 $
1+
0,
0.
#350000000
b100011 !
1"
b100011 $
1%
1,
1.
1/
#360000000
b100100 !
b100100 $
1*
0+
0,
0-
0.
00
#370000000
b100101 !
b100101 $
1,
1-
1.
#380000000
b100110 !
0"
b100110 $
0%
1+
0,
0-
0/
#390000000
b100111 !
1"
b100111 $
1%
1,
1-
1/
#400000000
b101000 !
0"
b101000 $
0%
1)
0*
0+
0,
0.
0/
#410000000
b101001 !
b101001 $
1,
#420000000
b101010 !
b101010 $
1+
0,
0-
#430000000
b101011 !
1"
b101011 $
1%
1,
1-
1.
1/
#440000000
b101100 !
0"
b101100 $
0%
1*
0+
0,
0.
0/
#450000000
b101101 !
1"
b101101 $
1%
1,
1.
1/
#460000000
b101110 !
b101110 $
1+
0,
0-
#470000000
b101111 !
b101111 $
1,
#480000000
b110000 !
0"
b110000 $
0%
1(
0)
0*
0+
0,
0.
0/
#490000000
b110001 !
1"
1#
b110001 $
1%
1&
1,
1-
1.
10
#500000000
b110010 !
0#
b110010 $
0&
1+
0,
0.
#510000000
b110011 !
1#
b110011 $
1&
1,
1.
1/
#520000000
b110100 !
0"
0#
b110100 $
0%
0&
1*
0+
0,
0-
0.
00
#530000000
b110101 !
1#
b110101 $
1&
1,
1-
1.
#540000000
b110110 !
0#
b110110 $
0&
1+
0,
0-
0/
#550000000
b110111 !
1#
b110111 $
1&
1,
1-
1/
#560000000
b111000 !
0#
b111000 $
0&
1)
0*
0+
0,
0.
0/
#570000000
b111001 !
1#
b111001 $
1&
1,
#580000000
b111010 !
0#
b111010 $
0&
1+
0,
0-
#590000000
b111011 !
1#
b111011 $
1&
1,
1-
1.
1/
#600000000
b111100 !
0#
b111100 $
0&
1*
0+
0,
0.
0/
#610000000
b111101 !
1#
b111101 $
1&
1,
1.
1/
#620000000
b111110 !
0#
b111110 $
0&
1+
0,
0-
#630000000
b111111 !
1#
b111111 $
1&
1,
#640000000
b000000 !
0#
b000000 $
0&
0'
0(
0)
0*
0+
0,
0.
0/
#650000000
b000001 !
1"
b000001 $
1%
1,
1-
1.
10
#660000000
b000010 !
b000010 $
1+
0,
0.
#670000000
b000011 !
b000011 $
1,
1.
1/
#680000000
b000100 !
0"
b000100 $
0%
1*
0+
0,
0-
0.
00
#690000000
b000101 !
1"
b000101 $
1%
1,
1-
1.
#700000000
b000110 !
0"
b000110 $
0%
1+
0,
0-
0/
#710000000
b000111 !
1"
b000111 $
1%
1,
1-
1/
#720000000
b001000 !
b001000 $
1)
0*
0+
0,
0.
0/
#730000000
b001001 !
b001001 $
1,
#740000000
b001010 !
0"
b001010 $
0%
1+
0,
0-
#750000000
b001011 !
1"
b001011 $
1%
1,
1-
1.
1/
#760000000
b001100 !
b001100 $
1*
0+
0,
0.
0/
#770000000
b001101 !
b001101 $
1,
1.
1/
#780000000
b001110 !
0"
b001110 $
0%
1+
0,
0-
#790000000
b001111 !
b001111 $
1,
#800000000
b010000 !
0"
b010000 $
0%
1(
0)
0*
0+
0,
0.
0/
#810000000
b010001 !
1"
b010001 $
1%
1,
1-
1.
10
#820000000
b010010 !
0"
b010010 $
0%
1+
0,
0.
#830000000
b010011 !
1"
b010011 $
1%
1,
1.
1/
#840000000
b010100 !
0"
b010100 $
0%
1*
0+
0,
0-
0.
00
#850000000
b010101 !
1"
b010101 $
1%
1,
1-
1.
#860000000
b010110 !
b010110 $
1+
0,
0-
0/
#870000000
b010111 !
b010111 $
1,
1-
1/
#880000000
b011000 !
0"
b011000 $
0%
1)
0*
0+
0,
0.
0/
#890000000
b011001 !
b011001 $
1,
#900000000
b011010 !
b011010 $
1+
0,
0-
#910000000
b011011 !
1"
b011011 $
1%
1,
1-
1.
1/
#920000000
b011100 !
0"
b011100 $
0%
1*
0+
0,
0.
0/
#930000000
b011101 !
1"
b011101 $
1%
1,
1.
1/
#940000000
b011110 !
b011110 $
1+
0,
0-
#950000000
b011111 !
b011111 $
1,
#960000000
b100000 !
0"
b100000 $
0%
1'
0(
0)
0*
0+
0,
0.
0/
#970000000
b100001 !
b100001 $
1,
1-
1.
10
#980000000
b100010 !
b100010 $
1+
0,
0.
#990000000
b100011 !
1"
b100011 $
1%
1,
1.
1/
#1000000000
b100100 !
b100100 $
1*
0+
0,
0-
0.
00
